musicale/__init__.py
musicale/api.py
musicale/constants.py
musicale/exceptions.py
musicale/processdef.py
musicale/util.py
theatre-0.0.1.dist-info/METADATA
theatre-0.0.1.dist-info/WHEEL
theatre-0.0.1.dist-info/top_level.txt
theatre-0.0.1.dist-info/RECORD
